e2xgradingtools/__init__.py
e2xgradingtools/__version__.py
e2xgradingtools/base.py
e2xgradingtools/classes.py
e2xgradingtools/comparators.py
e2xgradingtools/decorators.py
e2xgradingtools/functions.py
e2xgradingtools/utils.py
e2xgradingtools/variables.py
e2xgradingtools-0.0.4.dist-info/METADATA
e2xgradingtools-0.0.4.dist-info/WHEEL
e2xgradingtools-0.0.4.dist-info/licenses/LICENSE
e2xgradingtools-0.0.4.dist-info/RECORD
